<?xml version="1.0" encoding="UTF-8"?>
<dcpData>
  <ProfileName>IMG_8015</ProfileName>
  <CalibrationIlluminant1>21</CalibrationIlluminant1>
  <CalibrationIlluminant2>0</CalibrationIlluminant2>
  <ColorMatrix1 Rows="3" Cols="3">
    <Element Row="2" Col="2">0.526500</Element>
    <Element Row="2" Col="1">0.180600</Element>
    <Element Row="2" Col="0">-0.051500</Element>
    <Element Row="1" Col="2">0.331600</Element>
    <Element Row="1" Col="1">1.091300</Element>
    <Element Row="1" Col="0">-0.378400</Element>
    <Element Row="0" Col="2">0.012700</Element>
    <Element Row="0" Col="1">-0.128100</Element>
    <Element Row="0" Col="0">0.550900</Element>
  </ColorMatrix1>
  <ColorMatrix2 Rows="0" Cols="0"/>
  <ForwardMatrix1 Rows="0" Cols="0"/>
  <ForwardMatrix2 Rows="0" Cols="0"/>
  <ReductionMatrix1 Rows="0" Cols="0"/>
  <ReductionMatrix2 Rows="0" Cols="0"/>
  <EmbedPolicy>0</EmbedPolicy>
  <ProfileHueSatMapEncoding>0</ProfileHueSatMapEncoding>
  <HueSatDeltas1 hueDivisions="6" satDivisions="6" valDivisions="3">
    <Element HueDiv="0" SatDiv="0" ValDiv="0" HueShift="0.000000" SatScale="1.000000" ValScale="1.000000"/>
    <Element HueDiv="0" SatDiv="0" ValDiv="1" HueShift="0.000000" SatScale="1.000000" ValScale="1.000000"/>
    <Element HueDiv="0" SatDiv="0" ValDiv="2" HueShift="0.000000" SatScale="1.000000" ValScale="1.000000"/>
    <Element HueDiv="0" SatDiv="1" ValDiv="0" HueShift="0.000000" SatScale="1.000000" ValScale="1.000000"/>
    <Element HueDiv="0" SatDiv="1" ValDiv="1" HueShift="5.164987" SatScale="1.130651" ValScale="1.058505"/>
    <Element HueDiv="0" SatDiv="1" ValDiv="2" HueShift="7.823133" SatScale="1.003173" ValScale="1.198366"/>
    <Element HueDiv="0" SatDiv="2" ValDiv="0" HueShift="0.000000" SatScale="1.000000" ValScale="1.000000"/>
    <Element HueDiv="0" SatDiv="2" ValDiv="1" HueShift="2.085687" SatScale="1.127645" ValScale="0.992586"/>
    <Element HueDiv="0" SatDiv="2" ValDiv="2" HueShift="2.741765" SatScale="1.027411" ValScale="1.123113"/>
    <Element HueDiv="0" SatDiv="3" ValDiv="0" HueShift="0.000000" SatScale="1.000000" ValScale="1.000000"/>
    <Element HueDiv="0" SatDiv="3" ValDiv="1" HueShift="0.088970" SatScale="1.082969" ValScale="0.947092"/>
    <Element HueDiv="0" SatDiv="3" ValDiv="2" HueShift="0.188513" SatScale="1.013632" ValScale="1.056495"/>
    <Element HueDiv="0" SatDiv="4" ValDiv="0" HueShift="0.000000" SatScale="1.000000" ValScale="1.000000"/>
    <Element HueDiv="0" SatDiv="4" ValDiv="1" HueShift="-1.045443" SatScale="1.061595" ValScale="0.924081"/>
    <Element HueDiv="0" SatDiv="4" ValDiv="2" HueShift="-0.483675" SatScale="1.012798" ValScale="1.012556"/>
    <Element HueDiv="0" SatDiv="5" ValDiv="0" HueShift="0.000000" SatScale="1.000000" ValScale="1.000000"/>
    <Element HueDiv="0" SatDiv="5" ValDiv="1" HueShift="-0.735749" SatScale="1.015657" ValScale="0.978746"/>
    <Element HueDiv="0" SatDiv="5" ValDiv="2" HueShift="0.017494" SatScale="0.998965" ValScale="1.028123"/>
    <Element HueDiv="1" SatDiv="0" ValDiv="0" HueShift="0.000000" SatScale="1.000000" ValScale="1.000000"/>
    <Element HueDiv="1" SatDiv="0" ValDiv="1" HueShift="2.990080" SatScale="1.169706" ValScale="1.000000"/>
    <Element HueDiv="1" SatDiv="0" ValDiv="2" HueShift="8.849356" SatScale="1.115586" ValScale="1.000000"/>
    <Element HueDiv="1" SatDiv="1" ValDiv="0" HueShift="0.000000" SatScale="1.000000" ValScale="1.000000"/>
    <Element HueDiv="1" SatDiv="1" ValDiv="1" HueShift="2.990080" SatScale="1.169706" ValScale="1.097644"/>
    <Element HueDiv="1" SatDiv="1" ValDiv="2" HueShift="8.849356" SatScale="1.115586" ValScale="1.271765"/>
    <Element HueDiv="1" SatDiv="2" ValDiv="0" HueShift="0.000000" SatScale="1.000000" ValScale="1.000000"/>
    <Element HueDiv="1" SatDiv="2" ValDiv="1" HueShift="1.092464" SatScale="1.118976" ValScale="1.053064"/>
    <Element HueDiv="1" SatDiv="2" ValDiv="2" HueShift="4.456364" SatScale="1.052311" ValScale="1.221415"/>
    <Element HueDiv="1" SatDiv="3" ValDiv="0" HueShift="0.000000" SatScale="1.000000" ValScale="1.000000"/>
    <Element HueDiv="1" SatDiv="3" ValDiv="1" HueShift="0.251612" SatScale="1.074239" ValScale="1.010722"/>
    <Element HueDiv="1" SatDiv="3" ValDiv="2" HueShift="2.416412" SatScale="0.992731" ValScale="1.165142"/>
    <Element HueDiv="1" SatDiv="4" ValDiv="0" HueShift="0.000000" SatScale="1.000000" ValScale="1.000000"/>
    <Element HueDiv="1" SatDiv="4" ValDiv="1" HueShift="-0.812192" SatScale="1.017582" ValScale="0.995493"/>
    <Element HueDiv="1" SatDiv="4" ValDiv="2" HueShift="0.908961" SatScale="0.976470" ValScale="1.099120"/>
    <Element HueDiv="1" SatDiv="5" ValDiv="0" HueShift="0.000000" SatScale="1.000000" ValScale="1.000000"/>
    <Element HueDiv="1" SatDiv="5" ValDiv="1" HueShift="-0.876354" SatScale="0.991999" ValScale="1.009779"/>
    <Element HueDiv="1" SatDiv="5" ValDiv="2" HueShift="-0.233202" SatScale="0.991879" ValScale="1.037957"/>
    <Element HueDiv="2" SatDiv="0" ValDiv="0" HueShift="0.000000" SatScale="1.000000" ValScale="1.000000"/>
    <Element HueDiv="2" SatDiv="0" ValDiv="1" HueShift="-5.345510" SatScale="1.211267" ValScale="1.000000"/>
    <Element HueDiv="2" SatDiv="0" ValDiv="2" HueShift="0.026037" SatScale="1.134339" ValScale="1.000000"/>
    <Element HueDiv="2" SatDiv="1" ValDiv="0" HueShift="0.000000" SatScale="1.000000" ValScale="1.000000"/>
    <Element HueDiv="2" SatDiv="1" ValDiv="1" HueShift="-5.345510" SatScale="1.211267" ValScale="1.092441"/>
    <Element HueDiv="2" SatDiv="1" ValDiv="2" HueShift="0.026037" SatScale="1.134339" ValScale="1.257875"/>
    <Element HueDiv="2" SatDiv="2" ValDiv="0" HueShift="0.000000" SatScale="1.000000" ValScale="1.000000"/>
    <Element HueDiv="2" SatDiv="2" ValDiv="1" HueShift="-3.408186" SatScale="1.126057" ValScale="1.044204"/>
    <Element HueDiv="2" SatDiv="2" ValDiv="2" HueShift="1.795352" SatScale="1.039519" ValScale="1.180387"/>
    <Element HueDiv="2" SatDiv="3" ValDiv="0" HueShift="0.000000" SatScale="1.000000" ValScale="1.000000"/>
    <Element HueDiv="2" SatDiv="3" ValDiv="1" HueShift="0.208332" SatScale="1.020161" ValScale="0.997935"/>
    <Element HueDiv="2" SatDiv="3" ValDiv="2" HueShift="2.353567" SatScale="1.004643" ValScale="1.095814"/>
    <Element HueDiv="2" SatDiv="4" ValDiv="0" HueShift="0.000000" SatScale="1.000000" ValScale="1.000000"/>
    <Element HueDiv="2" SatDiv="4" ValDiv="1" HueShift="0.390394" SatScale="1.000653" ValScale="0.997756"/>
    <Element HueDiv="2" SatDiv="4" ValDiv="2" HueShift="0.323049" SatScale="0.993130" ValScale="1.026718"/>
    <Element HueDiv="2" SatDiv="5" ValDiv="0" HueShift="0.000000" SatScale="1.000000" ValScale="1.000000"/>
    <Element HueDiv="2" SatDiv="5" ValDiv="1" HueShift="0.171598" SatScale="0.991541" ValScale="1.042394"/>
    <Element HueDiv="2" SatDiv="5" ValDiv="2" HueShift="0.519969" SatScale="0.997330" ValScale="0.990814"/>
    <Element HueDiv="3" SatDiv="0" ValDiv="0" HueShift="0.000000" SatScale="1.000000" ValScale="1.000000"/>
    <Element HueDiv="3" SatDiv="0" ValDiv="1" HueShift="-7.973305" SatScale="1.059411" ValScale="1.000000"/>
    <Element HueDiv="3" SatDiv="0" ValDiv="2" HueShift="-8.225972" SatScale="1.102072" ValScale="1.000000"/>
    <Element HueDiv="3" SatDiv="1" ValDiv="0" HueShift="0.000000" SatScale="1.000000" ValScale="1.000000"/>
    <Element HueDiv="3" SatDiv="1" ValDiv="1" HueShift="-7.973305" SatScale="1.059411" ValScale="1.131455"/>
    <Element HueDiv="3" SatDiv="1" ValDiv="2" HueShift="-8.225972" SatScale="1.102072" ValScale="1.299376"/>
    <Element HueDiv="3" SatDiv="2" ValDiv="0" HueShift="0.000000" SatScale="1.000000" ValScale="1.000000"/>
    <Element HueDiv="3" SatDiv="2" ValDiv="1" HueShift="-5.511794" SatScale="1.023015" ValScale="1.128290"/>
    <Element HueDiv="3" SatDiv="2" ValDiv="2" HueShift="-3.846566" SatScale="1.020669" ValScale="1.270337"/>
    <Element HueDiv="3" SatDiv="3" ValDiv="0" HueShift="0.000000" SatScale="1.000000" ValScale="1.000000"/>
    <Element HueDiv="3" SatDiv="3" ValDiv="1" HueShift="-1.831868" SatScale="1.005135" ValScale="1.091257"/>
    <Element HueDiv="3" SatDiv="3" ValDiv="2" HueShift="0.358627" SatScale="1.001371" ValScale="1.194075"/>
    <Element HueDiv="3" SatDiv="4" ValDiv="0" HueShift="0.000000" SatScale="1.000000" ValScale="1.000000"/>
    <Element HueDiv="3" SatDiv="4" ValDiv="1" HueShift="0.467132" SatScale="1.001099" ValScale="1.059456"/>
    <Element HueDiv="3" SatDiv="4" ValDiv="2" HueShift="1.324870" SatScale="0.997276" ValScale="1.125807"/>
    <Element HueDiv="3" SatDiv="5" ValDiv="0" HueShift="0.000000" SatScale="1.000000" ValScale="1.000000"/>
    <Element HueDiv="3" SatDiv="5" ValDiv="1" HueShift="0.729206" SatScale="0.995340" ValScale="1.048683"/>
    <Element HueDiv="3" SatDiv="5" ValDiv="2" HueShift="0.753659" SatScale="0.993136" ValScale="1.074718"/>
    <Element HueDiv="4" SatDiv="0" ValDiv="0" HueShift="0.000000" SatScale="1.000000" ValScale="1.000000"/>
    <Element HueDiv="4" SatDiv="0" ValDiv="1" HueShift="-3.833879" SatScale="1.011094" ValScale="1.000000"/>
    <Element HueDiv="4" SatDiv="0" ValDiv="2" HueShift="-9.509322" SatScale="1.006897" ValScale="1.000000"/>
    <Element HueDiv="4" SatDiv="1" ValDiv="0" HueShift="0.000000" SatScale="1.000000" ValScale="1.000000"/>
    <Element HueDiv="4" SatDiv="1" ValDiv="1" HueShift="-3.833879" SatScale="1.011094" ValScale="1.118954"/>
    <Element HueDiv="4" SatDiv="1" ValDiv="2" HueShift="-9.509322" SatScale="1.006897" ValScale="1.266165"/>
    <Element HueDiv="4" SatDiv="2" ValDiv="0" HueShift="0.000000" SatScale="1.000000" ValScale="1.000000"/>
    <Element HueDiv="4" SatDiv="2" ValDiv="1" HueShift="-1.474146" SatScale="1.024537" ValScale="1.141714"/>
    <Element HueDiv="4" SatDiv="2" ValDiv="2" HueShift="-4.027318" SatScale="1.001604" ValScale="1.272946"/>
    <Element HueDiv="4" SatDiv="3" ValDiv="0" HueShift="0.000000" SatScale="1.000000" ValScale="1.000000"/>
    <Element HueDiv="4" SatDiv="3" ValDiv="1" HueShift="-0.534459" SatScale="1.019952" ValScale="1.145248"/>
    <Element HueDiv="4" SatDiv="3" ValDiv="2" HueShift="-1.542815" SatScale="0.998255" ValScale="1.202006"/>
    <Element HueDiv="4" SatDiv="4" ValDiv="0" HueShift="0.000000" SatScale="1.000000" ValScale="1.000000"/>
    <Element HueDiv="4" SatDiv="4" ValDiv="1" HueShift="0.082831" SatScale="1.017187" ValScale="1.035486"/>
    <Element HueDiv="4" SatDiv="4" ValDiv="2" HueShift="-0.252397" SatScale="1.000631" ValScale="1.091902"/>
    <Element HueDiv="4" SatDiv="5" ValDiv="0" HueShift="0.000000" SatScale="1.000000" ValScale="1.000000"/>
    <Element HueDiv="4" SatDiv="5" ValDiv="1" HueShift="0.063839" SatScale="1.000047" ValScale="1.030401"/>
    <Element HueDiv="4" SatDiv="5" ValDiv="2" HueShift="0.309354" SatScale="0.998778" ValScale="1.074924"/>
    <Element HueDiv="5" SatDiv="0" ValDiv="0" HueShift="0.000000" SatScale="1.000000" ValScale="1.000000"/>
    <Element HueDiv="5" SatDiv="0" ValDiv="1" HueShift="-5.347649" SatScale="0.964721" ValScale="1.000000"/>
    <Element HueDiv="5" SatDiv="0" ValDiv="2" HueShift="-7.910587" SatScale="0.846657" ValScale="1.000000"/>
    <Element HueDiv="5" SatDiv="1" ValDiv="0" HueShift="0.000000" SatScale="1.000000" ValScale="1.000000"/>
    <Element HueDiv="5" SatDiv="1" ValDiv="1" HueShift="-5.347649" SatScale="0.964721" ValScale="1.142152"/>
    <Element HueDiv="5" SatDiv="1" ValDiv="2" HueShift="-7.910587" SatScale="0.846657" ValScale="1.286416"/>
    <Element HueDiv="5" SatDiv="2" ValDiv="0" HueShift="0.000000" SatScale="1.000000" ValScale="1.000000"/>
    <Element HueDiv="5" SatDiv="2" ValDiv="1" HueShift="-6.207690" SatScale="1.003469" ValScale="1.174677"/>
    <Element HueDiv="5" SatDiv="2" ValDiv="2" HueShift="-5.489390" SatScale="0.925772" ValScale="1.258271"/>
    <Element HueDiv="5" SatDiv="3" ValDiv="0" HueShift="0.000000" SatScale="1.000000" ValScale="1.000000"/>
    <Element HueDiv="5" SatDiv="3" ValDiv="1" HueShift="-3.643440" SatScale="0.997340" ValScale="1.116329"/>
    <Element HueDiv="5" SatDiv="3" ValDiv="2" HueShift="-3.145458" SatScale="0.958681" ValScale="1.173556"/>
    <Element HueDiv="5" SatDiv="4" ValDiv="0" HueShift="0.000000" SatScale="1.000000" ValScale="1.000000"/>
    <Element HueDiv="5" SatDiv="4" ValDiv="1" HueShift="-1.701531" SatScale="0.999944" ValScale="1.061767"/>
    <Element HueDiv="5" SatDiv="4" ValDiv="2" HueShift="-1.022710" SatScale="0.983778" ValScale="1.086250"/>
    <Element HueDiv="5" SatDiv="5" ValDiv="0" HueShift="0.000000" SatScale="1.000000" ValScale="1.000000"/>
    <Element HueDiv="5" SatDiv="5" ValDiv="1" HueShift="-0.441155" SatScale="0.997524" ValScale="1.040462"/>
    <Element HueDiv="5" SatDiv="5" ValDiv="2" HueShift="-0.095896" SatScale="0.991650" ValScale="1.049864"/>
  </HueSatDeltas1>
  <UniqueCameraModelRestriction>iPhone9,3 back camera</UniqueCameraModelRestriction>
  <ProfileLookTableEncoding>0</ProfileLookTableEncoding>
  <BaselineExposureOffset>0.000000</BaselineExposureOffset>
  <DefaultBlackRender>0</DefaultBlackRender>
</dcpData>
